pdf/__init__.py
pdf/download_pdfs.py
pdf/extract_cells_from_table.py
pdf/extract_tables.py
pdf/prepare_pdfs.py
pdf/util.py
table_image_ocr/__init__.py
table_image_ocr/util.py
table_ocr/__init__.py
table_ocr/table-ocr.traineddata
table_ocr/util.py
table_ocr/demo/__init__.py
table_ocr/demo/__main__.py
table_ocr/extract_cells/__init__.py
table_ocr/extract_cells/__main__.py
table_ocr/extract_tables/__init__.py
table_ocr/extract_tables/__main__.py
table_ocr/ocr_image/__init__.py
table_ocr/ocr_image/__main__.py
table_ocr/ocr_to_csv/__init__.py
table_ocr/ocr_to_csv/__main__.py
table_ocr/pdf_to_images/__init__.py
table_ocr/pdf_to_images/__main__.py
table_ocr/tessdata/eng.traineddata
table_ocr/tessdata/table-ocr.traineddata
table_ocr-0.2.5.dist-info/LICENSE
table_ocr-0.2.5.dist-info/METADATA
table_ocr-0.2.5.dist-info/WHEEL
table_ocr-0.2.5.dist-info/top_level.txt
table_ocr-0.2.5.dist-info/RECORD
