Metadata-Version: 2.1
Name: table-ocr
Version: 0.2.5
Summary: Extract text from tables in images.
Home-page: https://github.com/eihli/image-table-ocr
Author: Eric Ihli
Author-email: eihli@owoga.com
License: UNKNOWN
Platform: UNKNOWN
Classifier: Programming Language :: Python :: 3
Classifier: License :: OSI Approved :: MIT License
Classifier: Operating System :: OS Independent
Requires-Python: >=3.6
Requires-Dist: pytesseract (~=0.3)
Requires-Dist: opencv-python (~=4.2)
Requires-Dist: numpy (~=1.19)
Requires-Dist: requests (>=2)
